{
  "annotations": {
    "list": [
      {
        "builtIn": 1,
        "datasource": {
          "type": "grafana",
          "uid": "-- Grafana --"
        },
        "enable": true,
        "hide": true,
        "iconColor": "rgba(0, 211, 255, 1)",
        "name": "Annotations & Alerts",
        "type": "dashboard"
      }
    ]
  },
  "editable": true,
  "fiscalYearStartMonth": 0,
  "graphTooltip": 0,
  "links": [],
  "panels": [
    {
      "datasource": {
        "type": "influxdb",
        "uid": "bfhay1m297a4gf"
      },
      "description": "Muestra el promedio de carga del sistema (Load Average). Representa la cantidad de procesos que se están ejecutando o que están en cola esperando por la CPU. Importante: No se mide en porcentaje. Un valor de 1.0 por cada núcleo (core) del procesador indica que el sistema está trabajando a su máxima capacidad sin demoras. Valores superiores al número de núcleos indican congestión y procesos atascados.",
      "fieldConfig": {
        "defaults": {
          "color": {
            "mode": "palette-classic"
          },
          "custom": {
            "axisBorderShow": false,
            "axisCenteredZero": false,
            "axisColorMode": "text",
            "axisLabel": "",
            "axisPlacement": "auto",
            "barAlignment": 0,
            "barWidthFactor": 0.6,
            "drawStyle": "line",
            "fillOpacity": 0,
            "gradientMode": "none",
            "hideFrom": {
              "legend": false,
              "tooltip": false,
              "viz": false
            },
            "insertNulls": false,
            "lineInterpolation": "linear",
            "lineWidth": 1,
            "pointSize": 5,
            "scaleDistribution": {
              "type": "linear"
            },
            "showPoints": "auto",
            "showValues": false,
            "spanNulls": false,
            "stacking": {
              "group": "A",
              "mode": "none"
            },
            "thresholdsStyle": {
              "mode": "line"
            }
          },
          "mappings": [],
          "thresholds": {
            "mode": "absolute",
            "steps": [
              {
                "color": "green",
                "value": 0
              },
              {
                "color": "red",
                "value": 2
              }
            ]
          }
        },
        "overrides": []
      },
      "gridPos": {
        "h": 8,
        "w": 23,
        "x": 0,
        "y": 0
      },
      "id": 5,
      "options": {
        "legend": {
          "calcs": [],
          "displayMode": "list",
          "placement": "bottom",
          "showLegend": true
        },
        "tooltip": {
          "hideZeros": false,
          "mode": "single",
          "sort": "none"
        }
      },
      "pluginVersion": "12.4.2",
      "targets": [
        {
          "query": "from(bucket: \"metricas_host\")\r\n  |> range(start: v.timeRangeStart, stop: v.timeRangeStop)\r\n  |> filter(fn: (r) => r._measurement == \"system\")\r\n  |> filter(fn: (r) => r._field == \"load1\")\r\n  |> filter(fn: (r) => r.host == \"${host}\")\r\n  |> aggregateWindow(every: v.windowPeriod, fn: mean, createEmpty: false)\r\n  |> yield(name: \"load_avg\")",
          "refId": "A"
        }
      ],
      "title": "Carga del Sistema",
      "type": "timeseries"
    },
    {
      "datasource": {
        "type": "influxdb",
        "uid": "bfhay1m297a4gf"
      },
      "fieldConfig": {
        "defaults": {
          "color": {
            "mode": "thresholds"
          },
          "displayName": "Service Available Last 24hr",
          "fieldMinMax": false,
          "mappings": [],
          "thresholds": {
            "mode": "absolute",
            "steps": [
              {
                "color": "green",
                "value": 0
              }
            ]
          },
          "unit": "percentunit"
        },
        "overrides": [
          {
            "matcher": {
              "id": "byFrameRefID",
              "options": "A"
            },
            "properties": []
          }
        ]
      },
      "gridPos": {
        "h": 8,
        "w": 11,
        "x": 0,
        "y": 8
      },
      "id": 3,
      "options": {
        "minVizHeight": 75,
        "minVizWidth": 75,
        "orientation": "auto",
        "reduceOptions": {
          "calcs": [
            "mean"
          ],
          "fields": "",
          "values": false
        },
        "showThresholdLabels": false,
        "showThresholdMarkers": true,
        "sizing": "auto"
      },
      "pluginVersion": "12.4.2",
      "targets": [
        {
          "query": "from(bucket: \"metricas_host\")\r\n  |> range(start: -24h)\r\n  |> filter(fn: (r) => r[\"_measurement\"] == \"http_response\")\r\n  |> filter(fn: (r) => r[\"_field\"] == \"estado_binario\")\r\n  |> filter(fn: (r) => r[\"host\"] == \"${host}\")\r\n  |> group(columns: [\"host\"])\r\n  |> aggregateWindow(every: v.windowPeriod, fn: mean, createEmpty: false)\r\n  |> yield(name: \"mean\")",
          "refId": "A"
        }
      ],
      "title": "Disponibilidad del servicio",
      "type": "gauge"
    },
    {
      "datasource": {
        "uid": "bfhay1m297a4gf"
      },
      "fieldConfig": {
        "defaults": {
          "color": {
            "mode": "thresholds"
          },
          "mappings": [
            {
              "options": {
                "0": {
                  "color": "red",
                  "index": 1,
                  "text": "OFFLINE"
                },
                "1": {
                  "color": "green",
                  "index": 0,
                  "text": "ONLINE"
                }
              },
              "type": "value"
            }
          ],
          "thresholds": {
            "mode": "percentage",
            "steps": [
              {
                "color": "green",
                "value": 0
              },
              {
                "color": "#EAB839",
                "value": 0
              }
            ]
          },
          "unit": "string"
        },
        "overrides": []
      },
      "gridPos": {
        "h": 8,
        "w": 12,
        "x": 11,
        "y": 8
      },
      "id": 4,
      "options": {
        "colorMode": "value",
        "graphMode": "area",
        "justifyMode": "auto",
        "orientation": "auto",
        "percentChangeColorMode": "standard",
        "reduceOptions": {
          "calcs": [
            "lastNotNull"
          ],
          "fields": "",
          "values": false
        },
        "showPercentChange": false,
        "textMode": "auto",
        "wideLayout": true
      },
      "pluginVersion": "12.4.2",
      "targets": [
        {
          "query": "from(bucket: \"metricas_host\")\r\n  |> range(start: v.timeRangeStart, stop: v.timeRangeStop)\r\n  |> filter(fn: (r) => r[\"_measurement\"] == \"http_response\")\r\n  |> filter(fn: (r) => r[\"_field\"] == \"estado_binario\")\r\n  |> filter(fn: (r) => r[\"host\"] == \"${host}\")\r\n  |> group(columns: [\"host\"])\r\n  |> aggregateWindow(every: v.windowPeriod, fn: mean, createEmpty: false)\r\n  |> yield(name: \"mean\")",
          "refId": "A"
        }
      ],
      "title": "Disponibilidad Actual",
      "type": "stat"
    },
    {
      "datasource": {
        "type": "influxdb",
        "uid": "bfhay1m297a4gf"
      },
      "fieldConfig": {
        "defaults": {
          "color": {
            "mode": "thresholds"
          },
          "mappings": [],
          "thresholds": {
            "mode": "absolute",
            "steps": [
              {
                "color": "green",
                "value": 0
              },
              {
                "color": "red",
                "value": 80
              }
            ]
          },
          "unit": "percent"
        },
        "overrides": [
          {
            "matcher": {
              "id": "byFrameRefID",
              "options": "CPU"
            },
            "properties": [
              {
                "id": "displayName",
                "value": "CPU Usage"
              }
            ]
          },
          {
            "matcher": {
              "id": "byFrameRefID",
              "options": "mem"
            },
            "properties": [
              {
                "id": "displayName",
                "value": "Memory Usage"
              }
            ]
          },
          {
            "matcher": {
              "id": "byFrameRefID",
              "options": "disk"
            },
            "properties": [
              {
                "id": "displayName",
                "value": "Disk Usage"
              }
            ]
          },
          {
            "matcher": {
              "id": "byFrameRefID",
              "options": "load"
            },
            "properties": [
              {
                "id": "displayName",
                "value": "System Load"
              }
            ]
          }
        ]
      },
      "gridPos": {
        "h": 11,
        "w": 11,
        "x": 0,
        "y": 16
      },
      "id": 1,
      "options": {
        "minVizHeight": 75,
        "minVizWidth": 75,
        "orientation": "auto",
        "reduceOptions": {
          "calcs": [
            "last"
          ],
          "fields": "",
          "values": false
        },
        "showThresholdLabels": true,
        "showThresholdMarkers": true,
        "sizing": "auto"
      },
      "pluginVersion": "12.4.2",
      "targets": [
        {
          "datasource": {
            "type": "influxdb",
            "uid": "bfhay1m297a4gf"
          },
          "query": "from(bucket: \"metricas_host\")\n  |> range(start: v.timeRangeStart, stop: v.timeRangeStop)\n  |> filter(fn: (r) => r._measurement == \"cpu\")\n  |> filter(fn: (r) => r.cpu == \"cpu-total\")\n  |> filter(fn: (r) => r._field == \"usage_idle\")\n  |> filter(fn: (r) => r.host == \"${host}\")\n  |> map(fn: (r) => ({r with _value: 100.0 - r._value}))\n  |> aggregateWindow(every: v.windowPeriod, fn: mean, createEmpty: false)\n  |> yield(name: \"cpu_usage\")",
          "refId": "CPU"
        },
        {
          "datasource": {
            "type": "influxdb",
            "uid": "bfhay1m297a4gf"
          },
          "query": "from(bucket: \"metricas_host\")\n  |> range(start: v.timeRangeStart, stop: v.timeRangeStop)\n  |> filter(fn: (r) => r._measurement == \"mem\")\n  |> filter(fn: (r) => r._field == \"used_percent\")\n  |> filter(fn: (r) => r.host == \"${host}\")\n  |> aggregateWindow(every: v.windowPeriod, fn: mean, createEmpty: false)\n  |> yield(name: \"mem_usage\")",
          "refId": "mem"
        },
        {
          "datasource": {
            "type": "influxdb",
            "uid": "bfhay1m297a4gf"
          },
          "query": "from(bucket: \"metricas_host\")\n  |> range(start: v.timeRangeStart, stop: v.timeRangeStop)\n  |> filter(fn: (r) => r._measurement == \"disk\")\n  |> filter(fn: (r) => r._field == \"used_percent\")\n  |> filter(fn: (r) => r.host == \"${host}\")\n  |> filter(fn: (r) => r.path == \"/\")\n  |> aggregateWindow(every: v.windowPeriod, fn: mean, createEmpty: false)\n  |> yield(name: \"disk_usage\")",
          "refId": "disk"
        },
        {
          "datasource": {
            "type": "influxdb",
            "uid": "bfhay1m297a4gf"
          },
          "query": "from(bucket: \"metricas_host\")\n  |> range(start: v.timeRangeStart, stop: v.timeRangeStop)\n  |> filter(fn: (r) => r._measurement == \"system\")\n  |> filter(fn: (r) => r._field == \"load1\")\n  |> filter(fn: (r) => r.host == \"${host}\")\n  |> aggregateWindow(every: v.windowPeriod, fn: mean, createEmpty: false)\n  |> yield(name: \"load_avg\")",
          "refId": "load"
        },
        {
          "datasource": {
            "type": "influxdb",
            "uid": "bfhay1m297a4gf"
          },
          "hide": true,
          "query": "from(bucket: \"metricas_host\")\r\n  |> range(start: -1h)\r\n  |> limit(n: 100)",
          "refId": "probar campos"
        }
      ],
      "title": "Usage %",
      "type": "gauge"
    },
    {
      "datasource": {
        "uid": "bfhay1m297a4gf"
      },
      "fieldConfig": {
        "defaults": {
          "color": {
            "mode": "thresholds"
          },
          "mappings": [],
          "thresholds": {
            "mode": "absolute",
            "steps": [
              {
                "color": "green",
                "value": 0
              }
            ]
          },
          "unit": "dtdhms"
        },
        "overrides": []
      },
      "gridPos": {
        "h": 11,
        "w": 12,
        "x": 11,
        "y": 16
      },
      "id": 2,
      "options": {
        "colorMode": "value",
        "graphMode": "area",
        "justifyMode": "auto",
        "orientation": "auto",
        "percentChangeColorMode": "standard",
        "reduceOptions": {
          "calcs": [
            "lastNotNull"
          ],
          "fields": "/^uptime vm\\-facultad$/",
          "values": false
        },
        "showPercentChange": false,
        "textMode": "auto",
        "wideLayout": true
      },
      "pluginVersion": "12.4.2",
      "targets": [
        {
          "query": "from(bucket: \"metricas_host\")\n  |> range(start: v.timeRangeStart, stop: v.timeRangeStop)\n  |> filter(fn: (r) => r._measurement == \"system\")\n  |> filter(fn: (r) => r._field == \"uptime\")\n  |> filter(fn: (r) => r.host == \"${host}\")\n  |> last()\n  |> yield(name: \"uptime\")",
          "refId": "A"
        }
      ],
      "title": "Uptime",
      "type": "stat"
    }
  ],
  "preload": false,
  "refresh": "5s",
  "schemaVersion": 42,
  "tags": [],
  "templating": {
    "list": [
      {
        "current": {
          "text": "vm-facultad",
          "value": "vm-facultad"
        },
        "datasource": {
          "type": "influxdb",
          "uid": "bfhay1m297a4gf"
        },
        "definition": "import \"influxdata/influxdb/schema\"\nschema.tagValues(bucket: \"metricas_host\", tag: \"host\")",
        "description": "Selector de Host",
        "name": "host",
        "options": [],
        "query": {
          "query": "import \"influxdata/influxdb/schema\"\nschema.tagValues(bucket: \"metricas_host\", tag: \"host\")"
        },
        "refresh": 1,
        "regex": "",
        "regexApplyTo": "value",
        "type": "query"
      }
    ]
  },
  "time": {
    "from": "now-6h",
    "to": "now"
  },
  "timepicker": {},
  "timezone": "browser",
  "title": "SOA_Grafana + InfluxDB",
  "uid": "adbfdlq",
  "version": 32,
  "weekStart": ""
}